fil/__init__.py
fil/py.typed
fil-1.4.2.dist-info/METADATA
fil-1.4.2.dist-info/WHEEL
fil-1.4.2.dist-info/RECORD
