Metadata-Version: 2.1
Name: fil
Version: 1.4.2
Summary: 🏺 Read/write JSON/TOML/Yaml/txt 🏺
License: MIT
Author: Tom Ritchford
Author-email: tom@swirly.com
Requires-Python: >=3.8
Classifier: License :: OSI Approved :: MIT License
Classifier: Programming Language :: Python :: 3
Classifier: Programming Language :: Python :: 3.8
Classifier: Programming Language :: Python :: 3.9
Classifier: Programming Language :: Python :: 3.10
Classifier: Programming Language :: Python :: 3.11
Requires-Dist: safer
Requires-Dist: types-ujson
